flow_control/__init__.py
flow_control/flow.py
flow_control/static/js/Specinjection.js
flow_control/static/js/injection.js
flow_control/tests/__init__.py
flow_control/tests/test_flowcontrol.py
flow_control_xblock-1.0.1.dist-info/LICENSE
flow_control_xblock-1.0.1.dist-info/METADATA
flow_control_xblock-1.0.1.dist-info/WHEEL
flow_control_xblock-1.0.1.dist-info/entry_points.txt
flow_control_xblock-1.0.1.dist-info/top_level.txt
flow_control_xblock-1.0.1.dist-info/RECORD
