Metadata-Version: 2.1
Name: flow-control-xblock
Version: 1.0.1
Summary: Flow Control XBlock
Home-page: https://github.com/eduNEXT/flow-control-xblock
Author: eduNEXT
Author-email: technical@edunext.co
License: UNKNOWN
Keywords: edunext xblock flowcontrol flow-control
Platform: UNKNOWN
Classifier: Framework :: Django :: 2.2
Classifier: Intended Audience :: Developers
Classifier: Intended Audience :: Education
Classifier: License :: OSI Approved :: GNU Affero General Public License v3
Classifier: Operating System :: OS Independent
Classifier: Programming Language :: Python
Classifier: Programming Language :: Python :: 3
Classifier: Programming Language :: Python :: 3.5
Classifier: Programming Language :: Python :: 3.8
Classifier: Topic :: Internet
Classifier: Topic :: Internet :: WWW/HTTP
Requires-Python: >=3.5.*
Requires-Dist: edx-opaque-keys[django]
Requires-Dist: xblock-utils
Requires-Dist: xblock
